buri/__init__.py
buri/buri.py
buri_tod-4.0.dist-info/METADATA
buri_tod-4.0.dist-info/WHEEL
buri_tod-4.0.dist-info/entry_points.txt
buri_tod-4.0.dist-info/RECORD
