Metadata-Version: 2.4
Name: buri-tod
Version: 4.0
Summary: B.U.R.I (Basic Universal Remote Interface) is a powerful, stateful, and user-friendly Python-based client for interacting with PHP webshells. Designed for penetration testers and security professionals, B.U.R.I demonstrates the impact of file upload vulnerabilities and provides a rich command-line interface for managing remote servers.
Project-URL: Homepage, https://github.com/joelindra/buri
Project-URL: Issues, https://github.com/joelindra/buri/issues
Author-email: Joel Indra <anonre@anonre.com>
Classifier: License :: OSI Approved :: MIT License
Classifier: Operating System :: OS Independent
Classifier: Programming Language :: Python :: 3
Requires-Python: >=3.7
Requires-Dist: prompt-toolkit
Requires-Dist: requests
Requires-Dist: rich
